supertape/__init__.py
supertape/cli/__init__.py
supertape/cli/__main__.py
supertape/cli/audio_manager.py
supertape/cli/commands/__init__.py
supertape/cli/commands/audio_commands.py
supertape/cli/commands/base.py
supertape/cli/commands/file_commands.py
supertape/cli/commands/history_commands.py
supertape/cli/commands/import_commands.py
supertape/cli/commands/registry.py
supertape/cli/commands/system_commands.py
supertape/cli/devices.py
supertape/cli/dump.py
supertape/cli/image_to_basic.py
supertape/cli/list.py
supertape/cli/listen.py
supertape/cli/play.py
supertape/cli/preprocess.py
supertape/cli/shell.py
supertape/cli/shell_completion.py
supertape/cli/shell_ui.py
supertape/core/__init__.py
supertape/core/asm/__init__.py
supertape/core/asm/assembler.py
supertape/core/asm/directives.py
supertape/core/asm/encoder.py
supertape/core/asm/errors.py
supertape/core/asm/lexer.py
supertape/core/asm/opcodes.py
supertape/core/asm/parser.py
supertape/core/asm/symbols.py
supertape/core/assembly/encode.py
supertape/core/audio/api.py
supertape/core/audio/device.py
supertape/core/audio/duration.py
supertape/core/audio/file_in.py
supertape/core/audio/file_out.py
supertape/core/audio/level.py
supertape/core/audio/modulation.py
supertape/core/audio/pipeline.py
supertape/core/audio/progress.py
supertape/core/audio/signal_in.py
supertape/core/audio/signal_out.py
supertape/core/basic/decode.py
supertape/core/basic/encode.py
supertape/core/basic/instruction.py
supertape/core/basic/minification.py
supertape/core/basic/opcodes.py
supertape/core/basic/preprocess.py
supertape/core/c/__init__.py
supertape/core/c/compiler.py
supertape/core/c/errors.py
supertape/core/config.py
supertape/core/disasm/__init__.py
supertape/core/disasm/m6803.py
supertape/core/disasm/py.typed
supertape/core/exceptions.py
supertape/core/file/api.py
supertape/core/file/block.py
supertape/core/file/byte_logger.py
supertape/core/file/bytes.py
supertape/core/file/container.py
supertape/core/file/load.py
supertape-1.0.0.dev11.dist-info/METADATA
supertape-1.0.0.dev11.dist-info/WHEEL
supertape-1.0.0.dev11.dist-info/entry_points.txt
supertape-1.0.0.dev11.dist-info/licenses/LICENSE
supertape-1.0.0.dev11.dist-info/RECORD
