Metadata-Version: 2.4
Name: supertape
Version: 1.0.0.dev11
Summary: Audio player/recorder software for legacy computers as tape recorder replacement
License: LICENSE
License-File: LICENSE
Keywords: audio,vintage,computers,tape,recorder,alice,tandy,mc-10
Author: Yannick Kirschhoffer
Author-email: alcibiade@alcibiade.org
Requires-Python: >=3.11,<3.14
Classifier: Development Status :: 4 - Beta
Classifier: Environment :: Console
Classifier: Intended Audience :: Developers
Classifier: Intended Audience :: End Users/Desktop
Classifier: License :: OSI Approved :: MIT License
Classifier: License :: Other/Proprietary License
Classifier: Operating System :: OS Independent
Classifier: Programming Language :: Python :: 3
Classifier: Programming Language :: Python :: 3.11
Classifier: Programming Language :: Python :: 3.12
Classifier: Programming Language :: Python :: 3.13
Classifier: Topic :: Multimedia :: Sound/Audio
Classifier: Topic :: System :: Emulators
Requires-Dist: PyYAML (>=6.0.2)
Requires-Dist: cython (>=3.0.11)
Requires-Dist: dulwich (>=0.24.10,<0.25.0)
Requires-Dist: imageio (>=2.36.0)
Requires-Dist: numpy (>=2.1.1)
Requires-Dist: prompt-toolkit (>=3.0.0)
Requires-Dist: pyaudio (>=0.2.14)
Requires-Dist: rich (>=13.0.0)
Requires-Dist: tabulate (>=0.9.0)
Project-URL: Documentation, https://github.com/supertape/supertape/
Project-URL: Homepage, https://github.com/supertape/supertape/
Project-URL: Repository, https://github.com/supertape/supertape/
